volosti_server_sanic/__init__.py
volosti_server_sanic/app.py
volosti_server_sanic/py.typed
volosti_server_sanic/wui/__init__.py
volosti_server_sanic/wui/main.py
volosti_server_sanic-0.1.dev1.dist-info/LICENSE
volosti_server_sanic-0.1.dev1.dist-info/WHEEL
volosti_server_sanic-0.1.dev1.dist-info/METADATA
volosti_server_sanic-0.1.dev1.dist-info/RECORD
